persunravelnp/__init__.py
persunravelnp/draw/__init__.py
persunravelnp/draw/_jinja_templates.py
persunravelnp/draw/_static_assets.py
persunravelnp/draw/frame.py
persunravelnp/draw/sizes.py
persunravelnp/draw/templates/markers.svg
persunravelnp/draw/templates/point-cloud-strip-background.svg
persunravelnp/draw/templates/style-n-defs.html
persunravelnp/draw/templates/unravelled-diagrams-dependent.svg
persunravelnp/draw/templates/unravelled-diagrams-standalone.svg
persunravelnp/draw/templates/unravelled-diagrams.css
persunravelnp/draw/viewbox.py
persunravelnp/kernel.py
persunravelnp/raster.py
persunravelnp/strip.py
persunravelnp/strip_section.py
persunravelnp/unravel.py
persunravelnp-0.0.2.dist-info/METADATA
persunravelnp-0.0.2.dist-info/WHEEL
persunravelnp-0.0.2.dist-info/RECORD
