Metadata-Version: 2.1
Name: persunravelnp
Version: 0.0.2
Summary: Kernel and Utilities for Unravelled Persistence Diagrams Using NumPy
Home-page: https://git.sr.ht/~bfluhr/persunravelnp
License: BSD-3-Clause
Author: Benedikt Fluhr
Author-email: pypi@bfluhr.com
Requires-Python: >=3.12
Classifier: License :: OSI Approved :: BSD License
Classifier: Programming Language :: Python :: 3
Classifier: Programming Language :: Python :: 3.12
Provides-Extra: draw
Requires-Dist: jinja2 (>=3.1) ; extra == "draw"
Requires-Dist: numpy (>=1.16)
Project-URL: Repository, https://git.sr.ht/~bfluhr/persunravelnp
